amalie-0.1.2.dist-info/METADATA
amalie-0.1.2.dist-info/WHEEL
amalie-0.1.2.dist-info/license_files/LICENSE
amalie/__init__.py
amalie/amalie.cpython-38-x86_64-linux-gnu.so
amalie-0.1.2.dist-info/RECORD
