Metadata-Version: 2.3
Name: amalie
Version: 0.1.2
Classifier: Programming Language :: Rust
Classifier: Programming Language :: Python :: Implementation :: CPython
Classifier: Programming Language :: Python :: Implementation :: PyPy
License-File: LICENSE
Summary: Mathmatical library written for rust and python
Keywords: math,algebra
Author: GlacierSG <iamglaciersg@gmail.com>
Author-email: GlacierSG <iamglaciersg@gmail.com>
License: MIT
Requires-Python: >=3.7
Project-URL: Source Code, https://github.com/GlacierSG/amalie
